Metadata-Version: 2.4
Name: yottactl
Version: 0.1.6
Summary: This is a lightweight library that works as a connector to Yottalabs public API.
Home-page: https://github.com/yottalabsai/yottactl
License: MIT
Keywords: yotta,Public API
Classifier: Intended Audience :: Developers
Classifier: Programming Language :: Python :: 3
Classifier: License :: OSI Approved :: MIT License
Classifier: Operating System :: OS Independent
Requires-Python: >=3.8
Requires-Dist: requests>=2.31.0
Dynamic: classifier
Dynamic: description
Dynamic: description-content-type
Dynamic: home-page
Dynamic: keywords
Dynamic: license
Dynamic: requires-dist
Dynamic: requires-python
Dynamic: summary
